hityper/__init__.py
hityper/__main__.py
hityper/config.py
hityper/rej_typerule.py
hityper/stdtypes.py
hityper/tdg.py
hityper/tdg_generator.py
hityper/typeobject.py
hityper/typerule.py
hityper/usertype_finder.py
hityper/utils.py
hityper-1.0.3.dist-info/LICENSE
hityper-1.0.3.dist-info/METADATA
hityper-1.0.3.dist-info/WHEEL
hityper-1.0.3.dist-info/entry_points.txt
hityper-1.0.3.dist-info/top_level.txt
hityper-1.0.3.dist-info/RECORD
