Metadata-Version: 2.1
Name: hityper
Version: 1.0.3
Summary: HiTyper: A hybrid type inference framework for Python
Home-page: https://github.com/JohnnyPeng18/HiTyper
Author: Yun Peng
Author-email: research@yunpeng.work
License: UNKNOWN
Keywords: python,type inference,static analysis
Platform: UNKNOWN
Classifier: Development Status :: 4 - Beta
Classifier: Programming Language :: Python :: 3.9
Classifier: Programming Language :: Python :: 3.10
Classifier: Intended Audience :: Science/Research
Classifier: License :: OSI Approved :: Apache Software License
Classifier: Topic :: Software Development :: Build Tools
License-File: LICENSE
Requires-Dist: astpretty (>=2.1.0)
Requires-Dist: pycg (>=0.0.4)
Requires-Dist: graphviz (>=0.19.0)
Requires-Dist: gensim (>=3.7.0)
Requires-Dist: regex (>=2022.3.15)
Requires-Dist: requests (>=2.27.0)
Requires-Dist: tqdm (>=4.63.0)
Requires-Dist: transformers (>=4.17.0)
Requires-Dist: Levenshtein (>=0.18.0)
Requires-Dist: func-timeout (>=4.3.5)
